[{"image_path": "G:\\data-CT\\NNUNET_RESULT\\NNUNET_RESULT\\20240822_pic\\B7.nii.gz.jpg", "target": 0}, {"image_path": "G:\\data-CT\\NNUNET_RESULT\\NNUNET_RESULT\\20240822_pic\\22.nii.gz.jpg", "target": 1}, {"image_path": "G:\\data-CT\\NNUNET_RESULT\\NNUNET_RESULT\\20240822_pic\\43.nii.gz.jpg", "target": 1}, {"image_path": "G:\\data-CT\\NNUNET_RESULT\\NNUNET_RESULT\\20240822_pic\\sd36.nii.gz.jpg", "target": 1}, {"image_path": "G:\\data-CT\\NNUNET_RESULT\\NNUNET_RESULT\\20240822_pic\\sdc22.nii.gz.jpg", "target": 1}, {"image_path": "G:\\data-CT\\NNUNET_RESULT\\NNUNET_RESULT\\20240822_pic\\SDB49.nii.gz.jpg", "target": 1}, {"image_path": "G:\\data-CT\\NNUNET_RESULT\\NNUNET_RESULT\\20240822_pic\\SDB32.nii.gz.jpg", "target": 1}, {"image_path": "G:\\data-CT\\NNUNET_RESULT\\NNUNET_RESULT\\20240822_pic\\D38.nii.gz.jpg", "target": 0}, {"image_path": "G:\\data-CT\\NNUNET_RESULT\\NNUNET_RESULT\\20240822_pic\\sd7.nii.gz.jpg", "target": 1}, {"image_path": "G:\\data-CT\\NNUNET_RESULT\\NNUNET_RESULT\\20240822_pic\\sdc36.nii.gz.jpg", "target": 1}, {"image_path": "G:\\data-CT\\NNUNET_RESULT\\NNUNET_RESULT\\20240822_pic\\SDA18.nii.gz.jpg", "target": 0}, {"image_path": "G:\\data-CT\\NNUNET_RESULT\\NNUNET_RESULT\\20240822_pic\\153.nii.gz.jpg", "target": 0}, {"image_path": "G:\\data-CT\\NNUNET_RESULT\\NNUNET_RESULT\\20240822_pic\\187.nii.gz.jpg", "target": 0}, {"image_path": "G:\\data-CT\\NNUNET_RESULT\\NNUNET_RESULT\\20240822_pic\\sdc14.nii.gz.jpg", "target": 1}, {"image_path": "G:\\data-CT\\NNUNET_RESULT\\NNUNET_RESULT\\20240822_pic\\B36.nii.gz.jpg", "target": 1}, {"image_path": "G:\\data-CT\\NNUNET_RESULT\\NNUNET_RESULT\\20240822_pic\\sd1.nii.gz.jpg", "target": 1}, {"image_path": "G:\\data-CT\\NNUNET_RESULT\\NNUNET_RESULT\\20240822_pic\\D99.nii.gz.jpg", "target": 1}, {"image_path": "G:\\data-CT\\NNUNET_RESULT\\NNUNET_RESULT\\20240822_pic\\A4.nii.gz.jpg", "target": 0}, {"image_path": "G:\\data-CT\\NNUNET_RESULT\\NNUNET_RESULT\\20240822_pic\\38.nii.gz.jpg", "target": 1}, {"image_path": "G:\\data-CT\\NNUNET_RESULT\\NNUNET_RESULT\\20240822_pic\\SDA2.nii.gz.jpg", "target": 0}, {"image_path": "G:\\data-CT\\NNUNET_RESULT\\NNUNET_RESULT\\20240822_pic\\62.nii.gz.jpg", "target": 0}, {"image_path": "G:\\data-CT\\NNUNET_RESULT\\NNUNET_RESULT\\20240822_pic\\sdc5.nii.gz.jpg", "target": 1}, {"image_path": "G:\\data-CT\\NNUNET_RESULT\\NNUNET_RESULT\\20240822_pic\\SDB51.nii.gz.jpg", "target": 0}, {"image_path": "G:\\data-CT\\NNUNET_RESULT\\NNUNET_RESULT\\20240822_pic\\sd48.nii.gz.jpg", "target": 1}, {"image_path": "G:\\data-CT\\NNUNET_RESULT\\NNUNET_RESULT\\20240822_pic\\SDA12.nii.gz.jpg", "target": 0}, {"image_path": "G:\\data-CT\\NNUNET_RESULT\\NNUNET_RESULT\\20240822_pic\\sdc35.nii.gz.jpg", "target": 1}, {"image_path": "G:\\data-CT\\NNUNET_RESULT\\NNUNET_RESULT\\20240822_pic\\C19.nii.gz.jpg", "target": 0}, {"image_path": "G:\\data-CT\\NNUNET_RESULT\\NNUNET_RESULT\\20240822_pic\\D31.nii.gz.jpg", "target": 1}, {"image_path": "G:\\data-CT\\NNUNET_RESULT\\NNUNET_RESULT\\20240822_pic\\sd20.nii.gz.jpg", "target": 1}, {"image_path": "G:\\data-CT\\NNUNET_RESULT\\NNUNET_RESULT\\20240822_pic\\SX14.nii.gz.jpg", "target": 1}, {"image_path": "G:\\data-CT\\NNUNET_RESULT\\NNUNET_RESULT\\20240822_pic\\B45.nii.gz.jpg", "target": 1}, {"image_path": "G:\\data-CT\\NNUNET_RESULT\\NNUNET_RESULT\\20240822_pic\\S43.nii.gz.jpg", "target": 0}, {"image_path": "G:\\data-CT\\NNUNET_RESULT\\NNUNET_RESULT\\20240822_pic\\S9.nii.gz.jpg", "target": 0}, {"image_path": "G:\\data-CT\\NNUNET_RESULT\\NNUNET_RESULT\\20240822_pic\\B18.nii.gz.jpg", "target": 0}, {"image_path": "G:\\data-CT\\NNUNET_RESULT\\NNUNET_RESULT\\20240822_pic\\sd9.nii.gz.jpg", "target": 1}, {"image_path": "G:\\data-CT\\NNUNET_RESULT\\NNUNET_RESULT\\20240822_pic\\D7.nii.gz.jpg", "target": 1}, {"image_path": "G:\\data-CT\\NNUNET_RESULT\\NNUNET_RESULT\\20240822_pic\\B42.nii.gz.jpg", "target": 0}, {"image_path": "G:\\data-CT\\NNUNET_RESULT\\NNUNET_RESULT\\20240822_pic\\D10.nii.gz.jpg", "target": 1}, {"image_path": "G:\\data-CT\\NNUNET_RESULT\\NNUNET_RESULT\\20240822_pic\\SDA26.nii.gz.jpg", "target": 0}, {"image_path": "G:\\data-CT\\NNUNET_RESULT\\NNUNET_RESULT\\20240822_pic\\104.nii.gz.jpg", "target": 1}, {"image_path": "G:\\data-CT\\NNUNET_RESULT\\NNUNET_RESULT\\20240822_pic\\sd61.nii.gz.jpg", "target": 1}, {"image_path": "G:\\data-CT\\NNUNET_RESULT\\NNUNET_RESULT\\20240822_pic\\sdc31.nii.gz.jpg", "target": 1}, {"image_path": "G:\\data-CT\\NNUNET_RESULT\\NNUNET_RESULT\\20240822_pic\\SDB11.nii.gz.jpg", "target": 0}, {"image_path": "G:\\data-CT\\NNUNET_RESULT\\NNUNET_RESULT\\20240822_pic\\SX11.nii.gz.jpg", "target": 0}, {"image_path": "G:\\data-CT\\NNUNET_RESULT\\NNUNET_RESULT\\20240822_pic\\152.nii.gz.jpg", "target": 1}, {"image_path": "G:\\data-CT\\NNUNET_RESULT\\NNUNET_RESULT\\20240822_pic\\A7.nii.gz.jpg", "target": 0}, {"image_path": "G:\\data-CT\\NNUNET_RESULT\\NNUNET_RESULT\\20240822_pic\\D12.nii.gz.jpg", "target": 1}, {"image_path": "G:\\data-CT\\NNUNET_RESULT\\NNUNET_RESULT\\20240822_pic\\SDB55.nii.gz.jpg", "target": 0}, {"image_path": "G:\\data-CT\\NNUNET_RESULT\\NNUNET_RESULT\\20240822_pic\\21.nii.gz.jpg", "target": 0}, {"image_path": "G:\\data-CT\\NNUNET_RESULT\\NNUNET_RESULT\\20240822_pic\\SDB63.nii.gz.jpg", "target": 0}, {"image_path": "G:\\data-CT\\NNUNET_RESULT\\NNUNET_RESULT\\20240822_pic\\sd40.nii.gz.jpg", "target": 1}, {"image_path": "G:\\data-CT\\NNUNET_RESULT\\NNUNET_RESULT\\20240822_pic\\27.nii.gz.jpg", "target": 1}, {"image_path": "G:\\data-CT\\NNUNET_RESULT\\NNUNET_RESULT\\20240822_pic\\sdc16.nii.gz.jpg", "target": 1}, {"image_path": "G:\\data-CT\\NNUNET_RESULT\\NNUNET_RESULT\\20240822_pic\\A28.nii.gz.jpg", "target": 0}, {"image_path": "G:\\data-CT\\NNUNET_RESULT\\NNUNET_RESULT\\20240822_pic\\190.nii.gz.jpg", "target": 1}, {"image_path": "G:\\data-CT\\NNUNET_RESULT\\NNUNET_RESULT\\20240822_pic\\SDB50.nii.gz.jpg", "target": 1}, {"image_path": "G:\\data-CT\\NNUNET_RESULT\\NNUNET_RESULT\\20240822_pic\\S41.nii.gz.jpg", "target": 0}, {"image_path": "G:\\data-CT\\NNUNET_RESULT\\NNUNET_RESULT\\20240822_pic\\S38.nii.gz.jpg", "target": 0}, {"image_path": "G:\\data-CT\\NNUNET_RESULT\\NNUNET_RESULT\\20240822_pic\\S22.nii.gz.jpg", "target": 0}, {"image_path": "G:\\data-CT\\NNUNET_RESULT\\NNUNET_RESULT\\20240822_pic\\sdc13.nii.gz.jpg", "target": 1}, {"image_path": "G:\\data-CT\\NNUNET_RESULT\\NNUNET_RESULT\\20240822_pic\\D40.nii.gz.jpg", "target": 0}, {"image_path": "G:\\data-CT\\NNUNET_RESULT\\NNUNET_RESULT\\20240822_pic\\A1.nii.gz.jpg", "target": 0}, {"image_path": "G:\\data-CT\\NNUNET_RESULT\\NNUNET_RESULT\\20240822_pic\\D48.nii.gz.jpg", "target": 1}, {"image_path": "G:\\data-CT\\NNUNET_RESULT\\NNUNET_RESULT\\20240822_pic\\C12.nii.gz.jpg", "target": 0}, {"image_path": "G:\\data-CT\\NNUNET_RESULT\\NNUNET_RESULT\\20240822_pic\\S21.nii.gz.jpg", "target": 1}, {"image_path": "G:\\data-CT\\NNUNET_RESULT\\NNUNET_RESULT\\20240822_pic\\A16.nii.gz.jpg", "target": 1}, {"image_path": "G:\\data-CT\\NNUNET_RESULT\\NNUNET_RESULT\\20240822_pic\\166.nii.gz.jpg", "target": 1}, {"image_path": "G:\\data-CT\\NNUNET_RESULT\\NNUNET_RESULT\\20240822_pic\\B23.nii.gz.jpg", "target": 0}, {"image_path": "G:\\data-CT\\NNUNET_RESULT\\NNUNET_RESULT\\20240822_pic\\A2.nii.gz.jpg", "target": 0}, {"image_path": "G:\\data-CT\\NNUNET_RESULT\\NNUNET_RESULT\\20240822_pic\\B5.nii.gz.jpg", "target": 1}, {"image_path": "G:\\data-CT\\NNUNET_RESULT\\NNUNET_RESULT\\20240822_pic\\SDA21.nii.gz.jpg", "target": 0}, {"image_path": "G:\\data-CT\\NNUNET_RESULT\\NNUNET_RESULT\\20240822_pic\\A20.nii.gz.jpg", "target": 0}, {"image_path": "G:\\data-CT\\NNUNET_RESULT\\NNUNET_RESULT\\20240822_pic\\SDB30.nii.gz.jpg", "target": 1}, {"image_path": "G:\\data-CT\\NNUNET_RESULT\\NNUNET_RESULT\\20240822_pic\\165.nii.gz.jpg", "target": 0}, {"image_path": "G:\\data-CT\\NNUNET_RESULT\\NNUNET_RESULT\\20240822_pic\\57.nii.gz.jpg", "target": 1}, {"image_path": "G:\\data-CT\\NNUNET_RESULT\\NNUNET_RESULT\\20240822_pic\\105.nii.gz.jpg", "target": 1}, {"image_path": "G:\\data-CT\\NNUNET_RESULT\\NNUNET_RESULT\\20240822_pic\\B50.nii.gz.jpg", "target": 1}, {"image_path": "G:\\data-CT\\NNUNET_RESULT\\NNUNET_RESULT\\20240822_pic\\B21.nii.gz.jpg", "target": 0}, {"image_path": "G:\\data-CT\\NNUNET_RESULT\\NNUNET_RESULT\\20240822_pic\\163.nii.gz.jpg", "target": 1}, {"image_path": "G:\\data-CT\\NNUNET_RESULT\\NNUNET_RESULT\\20240822_pic\\D41.nii.gz.jpg", "target": 1}, {"image_path": "G:\\data-CT\\NNUNET_RESULT\\NNUNET_RESULT\\20240822_pic\\sdc4.nii.gz.jpg", "target": 1}, {"image_path": "G:\\data-CT\\NNUNET_RESULT\\NNUNET_RESULT\\20240822_pic\\S1.nii.gz.jpg", "target": 0}, {"image_path": "G:\\data-CT\\NNUNET_RESULT\\NNUNET_RESULT\\20240822_pic\\SDA47.nii.gz.jpg", "target": 1}, {"image_path": "G:\\data-CT\\NNUNET_RESULT\\NNUNET_RESULT\\20240822_pic\\S28.nii.gz.jpg", "target": 0}, {"image_path": "G:\\data-CT\\NNUNET_RESULT\\NNUNET_RESULT\\20240822_pic\\B25.nii.gz.jpg", "target": 1}, {"image_path": "G:\\data-CT\\NNUNET_RESULT\\NNUNET_RESULT\\20240822_pic\\B9.nii.gz.jpg", "target": 1}, {"image_path": "G:\\data-CT\\NNUNET_RESULT\\NNUNET_RESULT\\20240822_pic\\sd52.nii.gz.jpg", "target": 1}, {"image_path": "G:\\data-CT\\NNUNET_RESULT\\NNUNET_RESULT\\20240822_pic\\197.nii.gz.jpg", "target": 0}, {"image_path": "G:\\data-CT\\NNUNET_RESULT\\NNUNET_RESULT\\20240822_pic\\SDB33.nii.gz.jpg", "target": 0}, {"image_path": "G:\\data-CT\\NNUNET_RESULT\\NNUNET_RESULT\\20240822_pic\\D70.nii.gz.jpg", "target": 1}, {"image_path": "G:\\data-CT\\NNUNET_RESULT\\NNUNET_RESULT\\20240822_pic\\SDB34.nii.gz.jpg", "target": 1}, {"image_path": "G:\\data-CT\\NNUNET_RESULT\\NNUNET_RESULT\\20240822_pic\\D65.nii.gz.jpg", "target": 1}, {"image_path": "G:\\data-CT\\NNUNET_RESULT\\NNUNET_RESULT\\20240822_pic\\sd17.nii.gz.jpg", "target": 1}, {"image_path": "G:\\data-CT\\NNUNET_RESULT\\NNUNET_RESULT\\20240822_pic\\sdc20.nii.gz.jpg", "target": 1}, {"image_path": "G:\\data-CT\\NNUNET_RESULT\\NNUNET_RESULT\\20240822_pic\\D52.nii.gz.jpg", "target": 1}, {"image_path": "G:\\data-CT\\NNUNET_RESULT\\NNUNET_RESULT\\20240822_pic\\D68.nii.gz.jpg", "target": 1}, {"image_path": "G:\\data-CT\\NNUNET_RESULT\\NNUNET_RESULT\\20240822_pic\\sd50.nii.gz.jpg", "target": 1}, {"image_path": "G:\\data-CT\\NNUNET_RESULT\\NNUNET_RESULT\\20240822_pic\\D79.nii.gz.jpg", "target": 1}, {"image_path": "G:\\data-CT\\NNUNET_RESULT\\NNUNET_RESULT\\20240822_pic\\SDB54.nii.gz.jpg", "target": 1}, {"image_path": "G:\\data-CT\\NNUNET_RESULT\\NNUNET_RESULT\\20240822_pic\\B30.nii.gz.jpg", "target": 0}, {"image_path": "G:\\data-CT\\NNUNET_RESULT\\NNUNET_RESULT\\20240822_pic\\107.nii.gz.jpg", "target": 1}, {"image_path": "G:\\data-CT\\NNUNET_RESULT\\NNUNET_RESULT\\20240822_pic\\29.nii.gz.jpg", "target": 0}, {"image_path": "G:\\data-CT\\NNUNET_RESULT\\NNUNET_RESULT\\20240822_pic\\sd34.nii.gz.jpg", "target": 1}, {"image_path": "G:\\data-CT\\NNUNET_RESULT\\NNUNET_RESULT\\20240822_pic\\D54.nii.gz.jpg", "target": 0}, {"image_path": "G:\\data-CT\\NNUNET_RESULT\\NNUNET_RESULT\\20240822_pic\\sd54.nii.gz.jpg", "target": 1}, {"image_path": "G:\\data-CT\\NNUNET_RESULT\\NNUNET_RESULT\\20240822_pic\\A8.nii.gz.jpg", "target": 1}, {"image_path": "G:\\data-CT\\NNUNET_RESULT\\NNUNET_RESULT\\20240822_pic\\D43.nii.gz.jpg", "target": 0}, {"image_path": "G:\\data-CT\\NNUNET_RESULT\\NNUNET_RESULT\\20240822_pic\\SDA17.nii.gz.jpg", "target": 0}, {"image_path": "G:\\data-CT\\NNUNET_RESULT\\NNUNET_RESULT\\20240822_pic\\SDA43.nii.gz.jpg", "target": 0}, {"image_path": "G:\\data-CT\\NNUNET_RESULT\\NNUNET_RESULT\\20240822_pic\\B15.nii.gz.jpg", "target": 0}, {"image_path": "G:\\data-CT\\NNUNET_RESULT\\NNUNET_RESULT\\20240822_pic\\SDB79.nii.gz.jpg", "target": 1}, {"image_path": "G:\\data-CT\\NNUNET_RESULT\\NNUNET_RESULT\\20240822_pic\\sd43.nii.gz.jpg", "target": 1}, {"image_path": "G:\\data-CT\\NNUNET_RESULT\\NNUNET_RESULT\\20240822_pic\\sdc37.nii.gz.jpg", "target": 1}, {"image_path": "G:\\data-CT\\NNUNET_RESULT\\NNUNET_RESULT\\20240822_pic\\sd57.nii.gz.jpg", "target": 1}, {"image_path": "G:\\data-CT\\NNUNET_RESULT\\NNUNET_RESULT\\20240822_pic\\SDB69.nii.gz.jpg", "target": 1}, {"image_path": "G:\\data-CT\\NNUNET_RESULT\\NNUNET_RESULT\\20240822_pic\\D22.nii.gz.jpg", "target": 0}, {"image_path": "G:\\data-CT\\NNUNET_RESULT\\NNUNET_RESULT\\20240822_pic\\sd16.nii.gz.jpg", "target": 1}, {"image_path": "G:\\data-CT\\NNUNET_RESULT\\NNUNET_RESULT\\20240822_pic\\B41.nii.gz.jpg", "target": 1}, {"image_path": "G:\\data-CT\\NNUNET_RESULT\\NNUNET_RESULT\\20240822_pic\\C22.nii.gz.jpg", "target": 0}, {"image_path": "G:\\data-CT\\NNUNET_RESULT\\NNUNET_RESULT\\20240822_pic\\D73.nii.gz.jpg", "target": 1}, {"image_path": "G:\\data-CT\\NNUNET_RESULT\\NNUNET_RESULT\\20240822_pic\\D71.nii.gz.jpg", "target": 1}, {"image_path": "G:\\data-CT\\NNUNET_RESULT\\NNUNET_RESULT\\20240822_pic\\sdc7.nii.gz.jpg", "target": 1}, {"image_path": "G:\\data-CT\\NNUNET_RESULT\\NNUNET_RESULT\\20240822_pic\\14.nii.gz.jpg", "target": 0}, {"image_path": "G:\\data-CT\\NNUNET_RESULT\\NNUNET_RESULT\\20240822_pic\\D93.nii.gz.jpg", "target": 1}, {"image_path": "G:\\data-CT\\NNUNET_RESULT\\NNUNET_RESULT\\20240822_pic\\B13.nii.gz.jpg", "target": 1}, {"image_path": "G:\\data-CT\\NNUNET_RESULT\\NNUNET_RESULT\\20240822_pic\\S30.nii.gz.jpg", "target": 0}, {"image_path": "G:\\data-CT\\NNUNET_RESULT\\NNUNET_RESULT\\20240822_pic\\S37.nii.gz.jpg", "target": 1}, {"image_path": "G:\\data-CT\\NNUNET_RESULT\\NNUNET_RESULT\\20240822_pic\\64.nii.gz.jpg", "target": 1}, {"image_path": "G:\\data-CT\\NNUNET_RESULT\\NNUNET_RESULT\\20240822_pic\\B19.nii.gz.jpg", "target": 1}, {"image_path": "G:\\data-CT\\NNUNET_RESULT\\NNUNET_RESULT\\20240822_pic\\SDA25.nii.gz.jpg", "target": 0}, {"image_path": "G:\\data-CT\\NNUNET_RESULT\\NNUNET_RESULT\\20240822_pic\\S29.nii.gz.jpg", "target": 0}, {"image_path": "G:\\data-CT\\NNUNET_RESULT\\NNUNET_RESULT\\20240822_pic\\S46.nii.gz.jpg", "target": 0}, {"image_path": "G:\\data-CT\\NNUNET_RESULT\\NNUNET_RESULT\\20240822_pic\\SDA45.nii.gz.jpg", "target": 1}, {"image_path": "G:\\data-CT\\NNUNET_RESULT\\NNUNET_RESULT\\20240822_pic\\SDB43.nii.gz.jpg", "target": 1}, {"image_path": "G:\\data-CT\\NNUNET_RESULT\\NNUNET_RESULT\\20240822_pic\\B28.nii.gz.jpg", "target": 0}, {"image_path": "G:\\data-CT\\NNUNET_RESULT\\NNUNET_RESULT\\20240822_pic\\171.nii.gz.jpg", "target": 0}, {"image_path": "G:\\data-CT\\NNUNET_RESULT\\NNUNET_RESULT\\20240822_pic\\SDA51.nii.gz.jpg", "target": 1}, {"image_path": "G:\\data-CT\\NNUNET_RESULT\\NNUNET_RESULT\\20240822_pic\\67.nii.gz.jpg", "target": 1}, {"image_path": "G:\\data-CT\\NNUNET_RESULT\\NNUNET_RESULT\\20240822_pic\\192.nii.gz.jpg", "target": 0}, {"image_path": "G:\\data-CT\\NNUNET_RESULT\\NNUNET_RESULT\\20240822_pic\\SDB17.nii.gz.jpg", "target": 0}, {"image_path": "G:\\data-CT\\NNUNET_RESULT\\NNUNET_RESULT\\20240822_pic\\A37.nii.gz.jpg", "target": 0}, {"image_path": "G:\\data-CT\\NNUNET_RESULT\\NNUNET_RESULT\\20240822_pic\\S57.nii.gz.jpg", "target": 1}, {"image_path": "G:\\data-CT\\NNUNET_RESULT\\NNUNET_RESULT\\20240822_pic\\sd13.nii.gz.jpg", "target": 1}, {"image_path": "G:\\data-CT\\NNUNET_RESULT\\NNUNET_RESULT\\20240822_pic\\B38.nii.gz.jpg", "target": 0}, {"image_path": "G:\\data-CT\\NNUNET_RESULT\\NNUNET_RESULT\\20240822_pic\\D53.nii.gz.jpg", "target": 1}, {"image_path": "G:\\data-CT\\NNUNET_RESULT\\NNUNET_RESULT\\20240822_pic\\sd60.nii.gz.jpg", "target": 1}, {"image_path": "G:\\data-CT\\NNUNET_RESULT\\NNUNET_RESULT\\20240822_pic\\117.nii.gz.jpg", "target": 1}, {"image_path": "G:\\data-CT\\NNUNET_RESULT\\NNUNET_RESULT\\20240822_pic\\SDB77.nii.gz.jpg", "target": 0}, {"image_path": "G:\\data-CT\\NNUNET_RESULT\\NNUNET_RESULT\\20240822_pic\\161.nii.gz.jpg", "target": 1}, {"image_path": "G:\\data-CT\\NNUNET_RESULT\\NNUNET_RESULT\\20240822_pic\\SDA13.nii.gz.jpg", "target": 0}, {"image_path": "G:\\data-CT\\NNUNET_RESULT\\NNUNET_RESULT\\20240822_pic\\196.nii.gz.jpg", "target": 0}, {"image_path": "G:\\data-CT\\NNUNET_RESULT\\NNUNET_RESULT\\20240822_pic\\S7.nii.gz.jpg", "target": 0}, {"image_path": "G:\\data-CT\\NNUNET_RESULT\\NNUNET_RESULT\\20240822_pic\\D55.nii.gz.jpg", "target": 1}, {"image_path": "G:\\data-CT\\NNUNET_RESULT\\NNUNET_RESULT\\20240822_pic\\167.nii.gz.jpg", "target": 1}, {"image_path": "G:\\data-CT\\NNUNET_RESULT\\NNUNET_RESULT\\20240822_pic\\D14.nii.gz.jpg", "target": 0}, {"image_path": "G:\\data-CT\\NNUNET_RESULT\\NNUNET_RESULT\\20240822_pic\\30.nii.gz.jpg", "target": 1}, {"image_path": "G:\\data-CT\\NNUNET_RESULT\\NNUNET_RESULT\\20240822_pic\\103.nii.gz.jpg", "target": 0}, {"image_path": "G:\\data-CT\\NNUNET_RESULT\\NNUNET_RESULT\\20240822_pic\\66.nii.gz.jpg", "target": 1}, {"image_path": "G:\\data-CT\\NNUNET_RESULT\\NNUNET_RESULT\\20240822_pic\\D3.nii.gz.jpg", "target": 1}, {"image_path": "G:\\data-CT\\NNUNET_RESULT\\NNUNET_RESULT\\20240822_pic\\B49.nii.gz.jpg", "target": 0}, {"image_path": "G:\\data-CT\\NNUNET_RESULT\\NNUNET_RESULT\\20240822_pic\\sdc24.nii.gz.jpg", "target": 1}, {"image_path": "G:\\data-CT\\NNUNET_RESULT\\NNUNET_RESULT\\20240822_pic\\SDB41.nii.gz.jpg", "target": 1}, {"image_path": "G:\\data-CT\\NNUNET_RESULT\\NNUNET_RESULT\\20240822_pic\\S25.nii.gz.jpg", "target": 1}, {"image_path": "G:\\data-CT\\NNUNET_RESULT\\NNUNET_RESULT\\20240822_pic\\A19.nii.gz.jpg", "target": 1}, {"image_path": "G:\\data-CT\\NNUNET_RESULT\\NNUNET_RESULT\\20240822_pic\\129.nii.gz.jpg", "target": 1}, {"image_path": "G:\\data-CT\\NNUNET_RESULT\\NNUNET_RESULT\\20240822_pic\\S58.nii.gz.jpg", "target": 0}, {"image_path": "G:\\data-CT\\NNUNET_RESULT\\NNUNET_RESULT\\20240822_pic\\SDA15.nii.gz.jpg", "target": 1}, {"image_path": "G:\\data-CT\\NNUNET_RESULT\\NNUNET_RESULT\\20240822_pic\\SDA50.nii.gz.jpg", "target": 1}, {"image_path": "G:\\data-CT\\NNUNET_RESULT\\NNUNET_RESULT\\20240822_pic\\D42.nii.gz.jpg", "target": 0}, {"image_path": "G:\\data-CT\\NNUNET_RESULT\\NNUNET_RESULT\\20240822_pic\\112.nii.gz.jpg", "target": 1}, {"image_path": "G:\\data-CT\\NNUNET_RESULT\\NNUNET_RESULT\\20240822_pic\\SDA30.nii.gz.jpg", "target": 0}, {"image_path": "G:\\data-CT\\NNUNET_RESULT\\NNUNET_RESULT\\20240822_pic\\D95.nii.gz.jpg", "target": 1}, {"image_path": "G:\\data-CT\\NNUNET_RESULT\\NNUNET_RESULT\\20240822_pic\\sd22.nii.gz.jpg", "target": 1}, {"image_path": "G:\\data-CT\\NNUNET_RESULT\\NNUNET_RESULT\\20240822_pic\\SDB21.nii.gz.jpg", "target": 0}, {"image_path": "G:\\data-CT\\NNUNET_RESULT\\NNUNET_RESULT\\20240822_pic\\18.nii.gz.jpg", "target": 1}, {"image_path": "G:\\data-CT\\NNUNET_RESULT\\NNUNET_RESULT\\20240822_pic\\sd29.nii.gz.jpg", "target": 1}, {"image_path": "G:\\data-CT\\NNUNET_RESULT\\NNUNET_RESULT\\20240822_pic\\SDB64.nii.gz.jpg", "target": 0}, {"image_path": "G:\\data-CT\\NNUNET_RESULT\\NNUNET_RESULT\\20240822_pic\\A25.nii.gz.jpg", "target": 0}, {"image_path": "G:\\data-CT\\NNUNET_RESULT\\NNUNET_RESULT\\20240822_pic\\S33.nii.gz.jpg", "target": 1}, {"image_path": "G:\\data-CT\\NNUNET_RESULT\\NNUNET_RESULT\\20240822_pic\\SDB40.nii.gz.jpg", "target": 0}, {"image_path": "G:\\data-CT\\NNUNET_RESULT\\NNUNET_RESULT\\20240822_pic\\S14.nii.gz.jpg", "target": 0}, {"image_path": "G:\\data-CT\\NNUNET_RESULT\\NNUNET_RESULT\\20240822_pic\\D30.nii.gz.jpg", "target": 0}, {"image_path": "G:\\data-CT\\NNUNET_RESULT\\NNUNET_RESULT\\20240822_pic\\A21.nii.gz.jpg", "target": 1}, {"image_path": "G:\\data-CT\\NNUNET_RESULT\\NNUNET_RESULT\\20240822_pic\\S17.nii.gz.jpg", "target": 1}, {"image_path": "G:\\data-CT\\NNUNET_RESULT\\NNUNET_RESULT\\20240822_pic\\156.nii.gz.jpg", "target": 1}, {"image_path": "G:\\data-CT\\NNUNET_RESULT\\NNUNET_RESULT\\20240822_pic\\121.nii.gz.jpg", "target": 0}, {"image_path": "G:\\data-CT\\NNUNET_RESULT\\NNUNET_RESULT\\20240822_pic\\76.nii.gz.jpg", "target": 0}, {"image_path": "G:\\data-CT\\NNUNET_RESULT\\NNUNET_RESULT\\20240822_pic\\sd41.nii.gz.jpg", "target": 1}, {"image_path": "G:\\data-CT\\NNUNET_RESULT\\NNUNET_RESULT\\20240822_pic\\D74.nii.gz.jpg", "target": 1}, {"image_path": "G:\\data-CT\\NNUNET_RESULT\\NNUNET_RESULT\\20240822_pic\\SDB81.nii.gz.jpg", "target": 1}, {"image_path": "G:\\data-CT\\NNUNET_RESULT\\NNUNET_RESULT\\20240822_pic\\65.nii.gz.jpg", "target": 1}, {"image_path": "G:\\data-CT\\NNUNET_RESULT\\NNUNET_RESULT\\20240822_pic\\SDA37.nii.gz.jpg", "target": 0}, {"image_path": "G:\\data-CT\\NNUNET_RESULT\\NNUNET_RESULT\\20240822_pic\\S4.nii.gz.jpg", "target": 1}, {"image_path": "G:\\data-CT\\NNUNET_RESULT\\NNUNET_RESULT\\20240822_pic\\sd32.nii.gz.jpg", "target": 1}, {"image_path": "G:\\data-CT\\NNUNET_RESULT\\NNUNET_RESULT\\20240822_pic\\SDA14.nii.gz.jpg", "target": 0}, {"image_path": "G:\\data-CT\\NNUNET_RESULT\\NNUNET_RESULT\\20240822_pic\\D18.nii.gz.jpg", "target": 0}, {"image_path": "G:\\data-CT\\NNUNET_RESULT\\NNUNET_RESULT\\20240822_pic\\SDB39.nii.gz.jpg", "target": 1}, {"image_path": "G:\\data-CT\\NNUNET_RESULT\\NNUNET_RESULT\\20240822_pic\\B43.nii.gz.jpg", "target": 1}, {"image_path": "G:\\data-CT\\NNUNET_RESULT\\NNUNET_RESULT\\20240822_pic\\157.nii.gz.jpg", "target": 1}, {"image_path": "G:\\data-CT\\NNUNET_RESULT\\NNUNET_RESULT\\20240822_pic\\B40.nii.gz.jpg", "target": 1}, {"image_path": "G:\\data-CT\\NNUNET_RESULT\\NNUNET_RESULT\\20240822_pic\\B3.nii.gz.jpg", "target": 1}, {"image_path": "G:\\data-CT\\NNUNET_RESULT\\NNUNET_RESULT\\20240822_pic\\23.nii.gz.jpg", "target": 1}, {"image_path": "G:\\data-CT\\NNUNET_RESULT\\NNUNET_RESULT\\20240822_pic\\160.nii.gz.jpg", "target": 1}, {"image_path": "G:\\data-CT\\NNUNET_RESULT\\NNUNET_RESULT\\20240822_pic\\33.nii.gz.jpg", "target": 1}, {"image_path": "G:\\data-CT\\NNUNET_RESULT\\NNUNET_RESULT\\20240822_pic\\C9.nii.gz.jpg", "target": 0}, {"image_path": "G:\\data-CT\\NNUNET_RESULT\\NNUNET_RESULT\\20240822_pic\\111.nii.gz.jpg", "target": 0}, {"image_path": "G:\\data-CT\\NNUNET_RESULT\\NNUNET_RESULT\\20240822_pic\\SDB76.nii.gz.jpg", "target": 0}, {"image_path": "G:\\data-CT\\NNUNET_RESULT\\NNUNET_RESULT\\20240822_pic\\sdc12.nii.gz.jpg", "target": 1}, {"image_path": "G:\\data-CT\\NNUNET_RESULT\\NNUNET_RESULT\\20240822_pic\\S18.nii.gz.jpg", "target": 1}, {"image_path": "G:\\data-CT\\NNUNET_RESULT\\NNUNET_RESULT\\20240822_pic\\sd59.nii.gz.jpg", "target": 1}, {"image_path": "G:\\data-CT\\NNUNET_RESULT\\NNUNET_RESULT\\20240822_pic\\SDB45.nii.gz.jpg", "target": 0}, {"image_path": "G:\\data-CT\\NNUNET_RESULT\\NNUNET_RESULT\\20240822_pic\\S54.nii.gz.jpg", "target": 1}, {"image_path": "G:\\data-CT\\NNUNET_RESULT\\NNUNET_RESULT\\20240822_pic\\D97.nii.gz.jpg", "target": 0}, {"image_path": "G:\\data-CT\\NNUNET_RESULT\\NNUNET_RESULT\\20240822_pic\\S13.nii.gz.jpg", "target": 0}, {"image_path": "G:\\data-CT\\NNUNET_RESULT\\NNUNET_RESULT\\20240822_pic\\SDA22.nii.gz.jpg", "target": 0}, {"image_path": "G:\\data-CT\\NNUNET_RESULT\\NNUNET_RESULT\\20240822_pic\\SDB74.nii.gz.jpg", "target": 0}, {"image_path": "G:\\data-CT\\NNUNET_RESULT\\NNUNET_RESULT\\20240822_pic\\sd19.nii.gz.jpg", "target": 1}, {"image_path": "G:\\data-CT\\NNUNET_RESULT\\NNUNET_RESULT\\20240822_pic\\sdc40.nii.gz.jpg", "target": 1}, {"image_path": "G:\\data-CT\\NNUNET_RESULT\\NNUNET_RESULT\\20240822_pic\\SDB75.nii.gz.jpg", "target": 0}, {"image_path": "G:\\data-CT\\NNUNET_RESULT\\NNUNET_RESULT\\20240822_pic\\SDA4.nii.gz.jpg", "target": 0}, {"image_path": "G:\\data-CT\\NNUNET_RESULT\\NNUNET_RESULT\\20240822_pic\\sd44.nii.gz.jpg", "target": 1}, {"image_path": "G:\\data-CT\\NNUNET_RESULT\\NNUNET_RESULT\\20240822_pic\\D75.nii.gz.jpg", "target": 0}, {"image_path": "G:\\data-CT\\NNUNET_RESULT\\NNUNET_RESULT\\20240822_pic\\D17.nii.gz.jpg", "target": 1}, {"image_path": "G:\\data-CT\\NNUNET_RESULT\\NNUNET_RESULT\\20240822_pic\\116.nii.gz.jpg", "target": 1}, {"image_path": "G:\\data-CT\\NNUNET_RESULT\\NNUNET_RESULT\\20240822_pic\\S2.nii.gz.jpg", "target": 0}, {"image_path": "G:\\data-CT\\NNUNET_RESULT\\NNUNET_RESULT\\20240822_pic\\D62.nii.gz.jpg", "target": 1}, {"image_path": "G:\\data-CT\\NNUNET_RESULT\\NNUNET_RESULT\\20240822_pic\\SDA49.nii.gz.jpg", "target": 0}, {"image_path": "G:\\data-CT\\NNUNET_RESULT\\NNUNET_RESULT\\20240822_pic\\sd31.nii.gz.jpg", "target": 1}, {"image_path": "G:\\data-CT\\NNUNET_RESULT\\NNUNET_RESULT\\20240822_pic\\A34.nii.gz.jpg", "target": 1}, {"image_path": "G:\\data-CT\\NNUNET_RESULT\\NNUNET_RESULT\\20240822_pic\\132.nii.gz.jpg", "target": 0}, {"image_path": "G:\\data-CT\\NNUNET_RESULT\\NNUNET_RESULT\\20240822_pic\\11.nii.gz.jpg", "target": 1}, {"image_path": "G:\\data-CT\\NNUNET_RESULT\\NNUNET_RESULT\\20240822_pic\\123.nii.gz.jpg", "target": 0}, {"image_path": "G:\\data-CT\\NNUNET_RESULT\\NNUNET_RESULT\\20240822_pic\\188.nii.gz.jpg", "target": 1}, {"image_path": "G:\\data-CT\\NNUNET_RESULT\\NNUNET_RESULT\\20240822_pic\\D94.nii.gz.jpg", "target": 1}, {"image_path": "G:\\data-CT\\NNUNET_RESULT\\NNUNET_RESULT\\20240822_pic\\102.nii.gz.jpg", "target": 1}, {"image_path": "G:\\data-CT\\NNUNET_RESULT\\NNUNET_RESULT\\20240822_pic\\sd37.nii.gz.jpg", "target": 1}, {"image_path": "G:\\data-CT\\NNUNET_RESULT\\NNUNET_RESULT\\20240822_pic\\A15.nii.gz.jpg", "target": 1}, {"image_path": "G:\\data-CT\\NNUNET_RESULT\\NNUNET_RESULT\\20240822_pic\\131.nii.gz.jpg", "target": 0}, {"image_path": "G:\\data-CT\\NNUNET_RESULT\\NNUNET_RESULT\\20240822_pic\\sd38.nii.gz.jpg", "target": 1}, {"image_path": "G:\\data-CT\\NNUNET_RESULT\\NNUNET_RESULT\\20240822_pic\\S6.nii.gz.jpg", "target": 0}, {"image_path": "G:\\data-CT\\NNUNET_RESULT\\NNUNET_RESULT\\20240822_pic\\32.nii.gz.jpg", "target": 0}, {"image_path": "G:\\data-CT\\NNUNET_RESULT\\NNUNET_RESULT\\20240822_pic\\SDA54.nii.gz.jpg", "target": 0}, {"image_path": "G:\\data-CT\\NNUNET_RESULT\\NNUNET_RESULT\\20240822_pic\\199.nii.gz.jpg", "target": 1}, {"image_path": "G:\\data-CT\\NNUNET_RESULT\\NNUNET_RESULT\\20240822_pic\\sd49.nii.gz.jpg", "target": 1}, {"image_path": "G:\\data-CT\\NNUNET_RESULT\\NNUNET_RESULT\\20240822_pic\\D25.nii.gz.jpg", "target": 1}, {"image_path": "G:\\data-CT\\NNUNET_RESULT\\NNUNET_RESULT\\20240822_pic\\SDB38.nii.gz.jpg", "target": 0}, {"image_path": "G:\\data-CT\\NNUNET_RESULT\\NNUNET_RESULT\\20240822_pic\\sdc8.nii.gz.jpg", "target": 1}, {"image_path": "G:\\data-CT\\NNUNET_RESULT\\NNUNET_RESULT\\20240822_pic\\B4.nii.gz.jpg", "target": 1}, {"image_path": "G:\\data-CT\\NNUNET_RESULT\\NNUNET_RESULT\\20240822_pic\\SDA46.nii.gz.jpg", "target": 1}, {"image_path": "G:\\data-CT\\NNUNET_RESULT\\NNUNET_RESULT\\20240822_pic\\sdc32.nii.gz.jpg", "target": 1}, {"image_path": "G:\\data-CT\\NNUNET_RESULT\\NNUNET_RESULT\\20240822_pic\\SDB16.nii.gz.jpg", "target": 0}, {"image_path": "G:\\data-CT\\NNUNET_RESULT\\NNUNET_RESULT\\20240822_pic\\S8.nii.gz.jpg", "target": 0}, {"image_path": "G:\\data-CT\\NNUNET_RESULT\\NNUNET_RESULT\\20240822_pic\\135.nii.gz.jpg", "target": 0}, {"image_path": "G:\\data-CT\\NNUNET_RESULT\\NNUNET_RESULT\\20240822_pic\\124.nii.gz.jpg", "target": 1}, {"image_path": "G:\\data-CT\\NNUNET_RESULT\\NNUNET_RESULT\\20240822_pic\\D34.nii.gz.jpg", "target": 0}, {"image_path": "G:\\data-CT\\NNUNET_RESULT\\NNUNET_RESULT\\20240822_pic\\D61.nii.gz.jpg", "target": 0}, {"image_path": "G:\\data-CT\\NNUNET_RESULT\\NNUNET_RESULT\\20240822_pic\\SX6.nii.gz.jpg", "target": 0}, {"image_path": "G:\\data-CT\\NNUNET_RESULT\\NNUNET_RESULT\\20240822_pic\\D57.nii.gz.jpg", "target": 0}, {"image_path": "G:\\data-CT\\NNUNET_RESULT\\NNUNET_RESULT\\20240822_pic\\D29.nii.gz.jpg", "target": 1}, {"image_path": "G:\\data-CT\\NNUNET_RESULT\\NNUNET_RESULT\\20240822_pic\\149.nii.gz.jpg", "target": 1}, {"image_path": "G:\\data-CT\\NNUNET_RESULT\\NNUNET_RESULT\\20240822_pic\\122.nii.gz.jpg", "target": 1}, {"image_path": "G:\\data-CT\\NNUNET_RESULT\\NNUNET_RESULT\\20240822_pic\\SDB62.nii.gz.jpg", "target": 1}, {"image_path": "G:\\data-CT\\NNUNET_RESULT\\NNUNET_RESULT\\20240822_pic\\S53.nii.gz.jpg", "target": 0}, {"image_path": "G:\\data-CT\\NNUNET_RESULT\\NNUNET_RESULT\\20240822_pic\\sd2.nii.gz.jpg", "target": 1}, {"image_path": "G:\\data-CT\\NNUNET_RESULT\\NNUNET_RESULT\\20240822_pic\\48.nii.gz.jpg", "target": 0}, {"image_path": "G:\\data-CT\\NNUNET_RESULT\\NNUNET_RESULT\\20240822_pic\\SDA52.nii.gz.jpg", "target": 0}, {"image_path": "G:\\data-CT\\NNUNET_RESULT\\NNUNET_RESULT\\20240822_pic\\D15.nii.gz.jpg", "target": 1}, {"image_path": "G:\\data-CT\\NNUNET_RESULT\\NNUNET_RESULT\\20240822_pic\\sd53.nii.gz.jpg", "target": 1}, {"image_path": "G:\\data-CT\\NNUNET_RESULT\\NNUNET_RESULT\\20240822_pic\\D64.nii.gz.jpg", "target": 1}, {"image_path": "G:\\data-CT\\NNUNET_RESULT\\NNUNET_RESULT\\20240822_pic\\SDA20.nii.gz.jpg", "target": 0}, {"image_path": "G:\\data-CT\\NNUNET_RESULT\\NNUNET_RESULT\\20240822_pic\\SDB61.nii.gz.jpg", "target": 0}, {"image_path": "G:\\data-CT\\NNUNET_RESULT\\NNUNET_RESULT\\20240822_pic\\sd3.nii.gz.jpg", "target": 1}, {"image_path": "G:\\data-CT\\NNUNET_RESULT\\NNUNET_RESULT\\20240822_pic\\SDA48.nii.gz.jpg", "target": 0}, {"image_path": "G:\\data-CT\\NNUNET_RESULT\\NNUNET_RESULT\\20240822_pic\\C17.nii.gz.jpg", "target": 1}, {"image_path": "G:\\data-CT\\NNUNET_RESULT\\NNUNET_RESULT\\20240822_pic\\B33.nii.gz.jpg", "target": 0}, {"image_path": "G:\\data-CT\\NNUNET_RESULT\\NNUNET_RESULT\\20240822_pic\\C2.nii.gz.jpg", "target": 0}, {"image_path": "G:\\data-CT\\NNUNET_RESULT\\NNUNET_RESULT\\20240822_pic\\SDB9.nii.gz.jpg", "target": 0}, {"image_path": "G:\\data-CT\\NNUNET_RESULT\\NNUNET_RESULT\\20240822_pic\\A22.nii.gz.jpg", "target": 1}, {"image_path": "G:\\data-CT\\NNUNET_RESULT\\NNUNET_RESULT\\20240822_pic\\sdc33.nii.gz.jpg", "target": 1}, {"image_path": "G:\\data-CT\\NNUNET_RESULT\\NNUNET_RESULT\\20240822_pic\\198.nii.gz.jpg", "target": 0}, {"image_path": "G:\\data-CT\\NNUNET_RESULT\\NNUNET_RESULT\\20240822_pic\\SDB4.nii.gz.jpg", "target": 1}, {"image_path": "G:\\data-CT\\NNUNET_RESULT\\NNUNET_RESULT\\20240822_pic\\S16.nii.gz.jpg", "target": 1}, {"image_path": "G:\\data-CT\\NNUNET_RESULT\\NNUNET_RESULT\\20240822_pic\\B20.nii.gz.jpg", "target": 1}, {"image_path": "G:\\data-CT\\NNUNET_RESULT\\NNUNET_RESULT\\20240822_pic\\SX9.nii.gz.jpg", "target": 0}, {"image_path": "G:\\data-CT\\NNUNET_RESULT\\NNUNET_RESULT\\20240822_pic\\45.nii.gz.jpg", "target": 0}, {"image_path": "G:\\data-CT\\NNUNET_RESULT\\NNUNET_RESULT\\20240822_pic\\D6.nii.gz.jpg", "target": 1}, {"image_path": "G:\\data-CT\\NNUNET_RESULT\\NNUNET_RESULT\\20240822_pic\\168.nii.gz.jpg", "target": 1}, {"image_path": "G:\\data-CT\\NNUNET_RESULT\\NNUNET_RESULT\\20240822_pic\\A35.nii.gz.jpg", "target": 0}, {"image_path": "G:\\data-CT\\NNUNET_RESULT\\NNUNET_RESULT\\20240822_pic\\sd46.nii.gz.jpg", "target": 1}, {"image_path": "G:\\data-CT\\NNUNET_RESULT\\NNUNET_RESULT\\20240822_pic\\SDB66.nii.gz.jpg", "target": 0}, {"image_path": "G:\\data-CT\\NNUNET_RESULT\\NNUNET_RESULT\\20240822_pic\\A27.nii.gz.jpg", "target": 0}]